README.md
setup.cfg
setup.py
etecsa_sdk.egg-info/PKG-INFO
etecsa_sdk.egg-info/SOURCES.txt
etecsa_sdk.egg-info/dependency_links.txt
etecsa_sdk.egg-info/requires.txt
etecsa_sdk.egg-info/top_level.txt
etecsasdk/__init__.py
etecsasdk/commercial/__init__.py
etecsasdk/commercial/ecrm/__init__.py
etecsasdk/commercial/ecrm/apiconstants.py
etecsasdk/commercial/ecrm/apicredentials.py
etecsasdk/commercial/ecrm/apioperations.py
etecsasdk/payment/__init__.py
etecsasdk/payment/transfermovil/__init__.py
etecsasdk/payment/transfermovil/apicredentials.py
etecsasdk/payment/transfermovil/apipayload.py
etecsasdk/payment/transfermovil/apipayment.py
etecsasdk/util/__init__.py
etecsasdk/util/apidevice/__init__.py
etecsasdk/util/apidevice/apidevice.py