Metadata-Version: 1.1
Name: etecsa-sdk
Version: 1.6
Summary: Etecsa SDK
Home-page: https://github.com/sebastiancuba/etecsa-sdk
Author: sebastian
Author-email: sebastian.rodriguez@etecsa.cu
License: MIT
Download-URL: https://github.com/sebastiancuba/etecsa-sdk/archive/v1.6.tar.gz
Keywords: sdk
Platform: UNKNOWN
Classifier: Programming Language :: Python :: 3.8
